sleap_share/__init__.py
sleap_share/auth.py
sleap_share/cli.py
sleap_share/client.py
sleap_share/config.py
sleap_share/exceptions.py
sleap_share/models.py
sleap_share-0.1.3.dist-info/METADATA
sleap_share-0.1.3.dist-info/WHEEL
sleap_share-0.1.3.dist-info/entry_points.txt
sleap_share-0.1.3.dist-info/RECORD
