Metadata-Version: 2.4
Name: sleap-share
Version: 0.1.3
Summary: Python client for SLEAP Share - upload and share SLEAP datasets
Project-URL: Homepage, https://slp.sh
Project-URL: Documentation, https://github.com/talmolab/sleap-share
Project-URL: Repository, https://github.com/talmolab/sleap-share
Project-URL: Issues, https://github.com/talmolab/sleap-share/issues
Author-email: Talmo Pereira <talmo@salk.edu>
License-Expression: MIT
Keywords: cli,data-sharing,pose-estimation,sleap
Classifier: Development Status :: 4 - Beta
Classifier: Environment :: Console
Classifier: Intended Audience :: Science/Research
Classifier: License :: OSI Approved :: MIT License
Classifier: Operating System :: OS Independent
Classifier: Programming Language :: Python :: 3
Classifier: Programming Language :: Python :: 3.11
Classifier: Programming Language :: Python :: 3.12
Classifier: Programming Language :: Python :: 3.13
Classifier: Topic :: Scientific/Engineering
Requires-Python: >=3.11
Requires-Dist: httpx>=0.25.0
Requires-Dist: platformdirs>=4.0.0
Requires-Dist: rich>=13.0.0
Requires-Dist: typer>=0.9.0
Provides-Extra: all
Requires-Dist: fsspec>=2024.0.0; extra == 'all'
Requires-Dist: keyring>=25.0.0; extra == 'all'
Provides-Extra: dev
Requires-Dist: mypy>=1.0.0; extra == 'dev'
Requires-Dist: pytest-cov>=4.0.0; extra == 'dev'
Requires-Dist: pytest-httpx>=0.30.0; extra == 'dev'
Requires-Dist: pytest>=8.0.0; extra == 'dev'
Requires-Dist: ruff>=0.8.0; extra == 'dev'
Provides-Extra: keyring
Requires-Dist: keyring>=25.0.0; extra == 'keyring'
Provides-Extra: lazy
Requires-Dist: fsspec>=2024.0.0; extra == 'lazy'
